rostypes/__init__.py
rostypes/builtinros.py
rostypes/constants.py
rostypes/loader.py
rostypes/tokens.py
rostypes/util.py
rostypes/values.py
ros_type_tokens-0.1.2.dist-info/LICENSE
ros_type_tokens-0.1.2.dist-info/METADATA
ros_type_tokens-0.1.2.dist-info/WHEEL
ros_type_tokens-0.1.2.dist-info/top_level.txt
ros_type_tokens-0.1.2.dist-info/RECORD
